Metadata-Version: 2.4
Name: unsloth_zoo
Version: 2026.1.2
Summary: Utils for Unsloth
Author: Unsloth AI team
Author-email: info@unsloth.ai
Maintainer-email: Daniel Han <danielhanchen@gmail.com>, Michael Han <info@unsloth.ai>
License-Expression: LGPL-3.0-or-later
Project-URL: homepage, http://www.unsloth.ai
Project-URL: documentation, https://github.com/unslothai/unsloth
Project-URL: repository, https://github.com/unslothai/unsloth
Keywords: ai,llm
Classifier: Programming Language :: Python
Requires-Python: <3.14,>=3.9
License-File: LICENSE
Requires-Dist: torch>=2.4.0
Requires-Dist: torchao>=0.13.0
Requires-Dist: triton>=3.0.0; "linux" in sys_platform
Requires-Dist: triton-windows; sys_platform == "win32" and (platform_machine == "AMD64" or platform_machine == "x86_64")
Requires-Dist: packaging>=24.1
Requires-Dist: tyro
Requires-Dist: transformers!=4.52.0,!=4.52.1,!=4.52.2,!=4.52.3,!=4.53.0,!=4.54.0,!=4.55.0,!=4.55.1,<=4.57.3,>=4.51.3
Requires-Dist: datasets!=4.0.*,!=4.1.0,<4.4.0,>=3.4.1
Requires-Dist: sentencepiece>=0.2.0
Requires-Dist: tqdm
Requires-Dist: psutil
Requires-Dist: wheel>=0.42.0
Requires-Dist: numpy
Requires-Dist: accelerate>=0.34.1
Requires-Dist: trl!=0.19.0,<=0.24.0,>=0.18.2
Requires-Dist: peft!=0.11.0,>=0.7.1
Requires-Dist: protobuf
Requires-Dist: huggingface_hub>=0.34.0
Requires-Dist: hf_transfer
Requires-Dist: cut_cross_entropy; python_version >= "3.10"
Requires-Dist: pillow
Requires-Dist: regex
Requires-Dist: msgspec
Requires-Dist: typing_extensions
Requires-Dist: filelock
Provides-Extra: huggingface
Requires-Dist: packaging>=24.1; extra == "huggingface"
Requires-Dist: tyro; extra == "huggingface"
Requires-Dist: transformers!=4.52.0,!=4.52.1,!=4.52.2,!=4.52.3,!=4.53.0,!=4.54.0,!=4.55.0,!=4.55.1,<=4.57.3,>=4.51.3; extra == "huggingface"
Requires-Dist: datasets!=4.0.*,!=4.1.0,<4.4.0,>=3.4.1; extra == "huggingface"
Requires-Dist: sentencepiece>=0.2.0; extra == "huggingface"
Requires-Dist: tqdm; extra == "huggingface"
Requires-Dist: psutil; extra == "huggingface"
Requires-Dist: wheel>=0.42.0; extra == "huggingface"
Requires-Dist: numpy; extra == "huggingface"
Requires-Dist: accelerate>=0.34.1; extra == "huggingface"
Requires-Dist: trl!=0.19.0,<=0.24.0,>=0.18.2; extra == "huggingface"
Requires-Dist: peft!=0.11.0,>=0.7.1; extra == "huggingface"
Requires-Dist: protobuf; extra == "huggingface"
Requires-Dist: huggingface_hub>=0.34.0; extra == "huggingface"
Requires-Dist: hf_transfer; extra == "huggingface"
Requires-Dist: cut_cross_entropy; python_version >= "3.10" and extra == "huggingface"
Requires-Dist: pillow; extra == "huggingface"
Requires-Dist: regex; extra == "huggingface"
Requires-Dist: msgspec; extra == "huggingface"
Requires-Dist: typing_extensions; extra == "huggingface"
Requires-Dist: filelock; extra == "huggingface"
Provides-Extra: base
Requires-Dist: unsloth_zoo[huggingface]; extra == "base"
Provides-Extra: intelgpu
Requires-Dist: torch>=2.4.0; extra == "intelgpu"
Requires-Dist: triton>=3.0.0; "linux" in sys_platform and extra == "intelgpu"
Requires-Dist: unsloth_zoo[huggingface]; extra == "intelgpu"
Dynamic: license-file
